certificate_cli/__init__.py
certificate_cli/__main__.py
certificate_cli/main.py
certificate_cli/pki_helpers.py
certificate_cli-0.2.5.dist-info/entry_points.txt
certificate_cli-0.2.5.dist-info/WHEEL
certificate_cli-0.2.5.dist-info/METADATA
certificate_cli-0.2.5.dist-info/RECORD
