Metadata-Version: 2.1
Name: certificate-cli
Version: 0.2.5
Summary: A collection of tools to aid in certificate testing
Home-page: https://github.com/tukanuk/certificate_server
Author: Ben Davidson
Author-email: ben.davidson@dynatrace.com
Requires-Python: >=3.11,<4.0
Classifier: License :: OSI Approved :: MIT License
Classifier: Operating System :: OS Independent
Classifier: Programming Language :: Python :: 3
Classifier: Programming Language :: Python :: 3
Requires-Dist: Flask (>=3.0.3,<4.0.0)
Requires-Dist: cryptography (>=43.0.0,<44.0.0)
Requires-Dist: typer[all] (>=0.12.4,<0.13.0)
Project-URL: Repository, https://github.com/tukanuk/certificate_server
